analysis.py
config.py
pre_processing.py
ece143_direct_marketing-1.0.dist-info/METADATA
ece143_direct_marketing-1.0.dist-info/WHEEL
ece143_direct_marketing-1.0.dist-info/top_level.txt
ece143_direct_marketing-1.0.dist-info/RECORD
