Metadata-Version: 2.1
Name: ece143-direct-marketing
Version: 1.0
Summary: Analysis tools for UCI Bank Marketing dataset
Home-page: https://github.com/sepehrfrgh/ece143_direct_marketing
Author: Ian Pegg - Hao Zhao - Harshita Krishna - Sepehr Foroughi
Author-email: ipegg@eng.ucsd.edu
License: UNKNOWN
Platform: UNKNOWN
